nanome_loaders/PPTConverter.py
nanome_loaders/URLLoader.py
nanome_loaders/WebLoader.py
nanome_loaders/WebLoaderServer.py
nanome_loaders/__init__.py
nanome_loaders/Menu/ImageTab.json
nanome_loaders/Menu/ListItem.json
nanome_loaders/Menu/MenuManager.py
nanome_loaders/Menu/PPTTab.json
nanome_loaders/Menu/UpIcon.png
nanome_loaders/Menu/WebLoad.json
nanome_loaders/WebUI/dist/favicon.ico
nanome_loaders/WebUI/dist/index.html
nanome_loaders/WebUI/dist/css/app.45cb7d44.css
nanome_loaders/WebUI/dist/img/logo.b8308220.png
nanome_loaders/WebUI/dist/js/app.35b51145.js
nanome_loaders/WebUI/dist/js/app.35b51145.js.map
nanome_loaders/WebUI/dist/js/chunk-vendors.bbae0fa9.js
nanome_loaders/WebUI/dist/js/chunk-vendors.bbae0fa9.js.map
nanome_loaders-1.0.3.dist-info/LICENSE
nanome_loaders-1.0.3.dist-info/METADATA
nanome_loaders-1.0.3.dist-info/WHEEL
nanome_loaders-1.0.3.dist-info/entry_points.txt
nanome_loaders-1.0.3.dist-info/top_level.txt
nanome_loaders-1.0.3.dist-info/RECORD
